pyzaim/__init__.py
pyzaim/pyzaim.py
pyzaim-1.1.0.dist-info/LICENSE
pyzaim-1.1.0.dist-info/METADATA
pyzaim-1.1.0.dist-info/WHEEL
pyzaim-1.1.0.dist-info/RECORD
