Metadata-Version: 2.1
Name: pyzaim
Version: 1.1.0
Summary: Zaimのデータを取得・操作するPythonパッケージ
Home-page: https://github.com/liebe-magi/pyzaim
License: MIT
Keywords: zaim,oauth,rest api,selenium,chromedriver
Author: liebe-magi
Author-email: liebe.magi@gmail.com
Requires-Python: >=3.7,<4.0
Classifier: License :: OSI Approved :: MIT License
Classifier: Programming Language :: Python :: 3
Classifier: Programming Language :: Python :: 3.7
Classifier: Programming Language :: Python :: 3.8
Classifier: Programming Language :: Python :: 3.9
Classifier: Programming Language :: Python :: 3.10
Classifier: Programming Language :: Python :: 3.11
Classifier: Programming Language :: Python :: 3.12
Requires-Dist: requests-oauthlib (==2.0.0)
Requires-Dist: selenium (==4.11.2)
Requires-Dist: tqdm (==4.66.2)
Project-URL: Repository, https://github.com/liebe-magi/pyzaim
